README.md
setup.py
django_error_assist/__init__.py
django_error_assist/exceptions.py
django_error_assist/middleware.py
django_error_assist.egg-info/PKG-INFO
django_error_assist.egg-info/SOURCES.txt
django_error_assist.egg-info/dependency_links.txt
django_error_assist.egg-info/not-zip-safe
django_error_assist.egg-info/requires.txt
django_error_assist.egg-info/top_level.txt